GithubManyouZhinan/README.md
GithubManyouZhinan/__init__.py
GithubManyouZhinan/__main__.py
GithubManyouZhinan/file.epub
GithubManyouZhinan/index.html
GithubManyouZhinan/css/__init__.py
GithubManyouZhinan/css/annotations.css
GithubManyouZhinan/css/main.css
GithubManyouZhinan/css/normalize.css
GithubManyouZhinan/css/popup.css
GithubManyouZhinan/font/__init__.py
GithubManyouZhinan/font/fontello.eot
GithubManyouZhinan/font/fontello.svg
GithubManyouZhinan/font/fontello.ttf
GithubManyouZhinan/font/fontello.woff
GithubManyouZhinan/img/__init__.py
GithubManyouZhinan/img/annotator-glyph-sprite.png
GithubManyouZhinan/img/annotator-icon-sprite.png
GithubManyouZhinan/img/apple-touch-icon.png
GithubManyouZhinan/img/cancelfullscreen.png
GithubManyouZhinan/img/close.png
GithubManyouZhinan/img/fullscreen.png
GithubManyouZhinan/img/loader.gif
GithubManyouZhinan/img/menu-icon.png
GithubManyouZhinan/img/save.png
GithubManyouZhinan/img/saved.png
GithubManyouZhinan/img/settings-s.png
GithubManyouZhinan/img/settings.png
GithubManyouZhinan/img/star.png
GithubManyouZhinan/js/__init__.py
GithubManyouZhinan/js/epub.js
GithubManyouZhinan/js/epub.min.js
GithubManyouZhinan/js/epub.min.map
GithubManyouZhinan/js/hooks.min.js
GithubManyouZhinan/js/hooks.min.map
GithubManyouZhinan/js/reader.js
GithubManyouZhinan/js/reader.js.map
GithubManyouZhinan/js/reader.min.js
GithubManyouZhinan/js/reader.min.map
GithubManyouZhinan/js/hooks/__init__.py
GithubManyouZhinan/js/hooks/extensions/__init__.py
GithubManyouZhinan/js/hooks/extensions/highlight.js
GithubManyouZhinan/js/libs/__init__.py
GithubManyouZhinan/js/libs/jquery.min.js
GithubManyouZhinan/js/libs/localforage.min.js
GithubManyouZhinan/js/libs/screenfull.js
GithubManyouZhinan/js/libs/screenfull.min.js
GithubManyouZhinan/js/libs/zip.min.js
GithubManyouZhinan/js/plugins/__init__.py
GithubManyouZhinan/js/plugins/hypothesis.js
GithubManyouZhinan/js/plugins/search.js
github_manyou_zhinan-2024.3.1.0.dist-info/METADATA
github_manyou_zhinan-2024.3.1.0.dist-info/WHEEL
github_manyou_zhinan-2024.3.1.0.dist-info/entry_points.txt
github_manyou_zhinan-2024.3.1.0.dist-info/top_level.txt
github_manyou_zhinan-2024.3.1.0.dist-info/RECORD
